spyre/Exceptions.py
spyre/__init__.py
spyre/client.py
spyre/crm.py
spyre/customers.py
spyre/inventory.py
spyre/sales.py
spyre/spire.py
spyre/utils.py
spyre/Models/__init__.py
spyre/Models/customers_models.py
spyre/Models/inventory_models.py
spyre/Models/sales_models.py
spyre/Models/shared_models.py
spyreapi-0.0.7.dist-info/licenses/LICENSE
spyreapi-0.0.7.dist-info/METADATA
spyreapi-0.0.7.dist-info/WHEEL
spyreapi-0.0.7.dist-info/top_level.txt
spyreapi-0.0.7.dist-info/RECORD
