Metadata-Version: 2.4
Name: spyreapi
Version: 0.0.7
Summary: A robust and extensible Python client for interacting with the [Spire Business Software API](https://developer.spiresystems.com/reference). This client provides an object-oriented interface to get, create, update, delete, query, filter, sort, and manage various Spire modules such as Sales Orders, Invoices, Inventory Items, and more.
Author-email: Sanjid Sharaf <sanjidsharaf1@gmail.com>
License-Expression: MIT
Project-URL: Homepage, https://github.com/sanjid-sharaf/spyre/
Project-URL: Issues, https://github.com/sanjid-sharaf/spyre/issues
Classifier: Programming Language :: Python :: 3
Classifier: Operating System :: OS Independent
Requires-Python: >=3.9
License-File: LICENSE
Requires-Dist: requests>=2.32.0
Requires-Dist: httpx>=0.28.0
Requires-Dist: pydantic>=2.11.0
Requires-Dist: python-dotenv>=1.1.0
Requires-Dist: pandas>=2.3.0
Requires-Dist: openpyxl>=3.1.5
Requires-Dist: numpy>=2.3.0
Dynamic: license-file
